MANIFEST.in
README.txt
plonetheme.mimbo-configure.zcml
pypi_upload.sh
setup.cfg
setup.py
docs/HISTORY.txt
docs/INSTALL.txt
docs/LICENSE.GPL
docs/LICENSE.txt
docs/TODO.txt
plonetheme/__init__.py
plonetheme.mimbo.egg-info/PKG-INFO
plonetheme.mimbo.egg-info/SOURCES.txt
plonetheme.mimbo.egg-info/dependency_links.txt
plonetheme.mimbo.egg-info/entry_points.txt
plonetheme.mimbo.egg-info/namespace_packages.txt
plonetheme.mimbo.egg-info/not-zip-safe
plonetheme.mimbo.egg-info/requires.txt
plonetheme.mimbo.egg-info/top_level.txt
plonetheme/mimbo/__init__.py
plonetheme/mimbo/configure.zcml
plonetheme/mimbo/profiles.zcml
plonetheme/mimbo/setuphandlers.py
plonetheme/mimbo/skins.zcml
plonetheme/mimbo/tests.py
plonetheme/mimbo/version.txt
plonetheme/mimbo/browser/__init__.py
plonetheme/mimbo/browser/configure.zcml
plonetheme/mimbo/browser/footer.pt
plonetheme/mimbo/browser/interfaces.py
plonetheme/mimbo/browser/personal_bar.pt
plonetheme/mimbo/browser/viewlet.pt
plonetheme/mimbo/browser/viewlets.py
plonetheme/mimbo/browser/images/README.txt
plonetheme/mimbo/browser/stylesheets/README.txt
plonetheme/mimbo/browser/stylesheets/main.css
plonetheme/mimbo/browser/stylesheets/print.css
plonetheme/mimbo/profiles/default/cssregistry.xml
plonetheme/mimbo/profiles/default/import_steps.xml
plonetheme/mimbo/profiles/default/jsregistry.xml
plonetheme/mimbo/profiles/default/metadata.xml
plonetheme/mimbo/profiles/default/plonetheme.mimbo_various.txt
plonetheme/mimbo/profiles/default/skins.xml
plonetheme/mimbo/profiles/default/viewlets.xml
plonetheme/mimbo/skins/plonetheme_mimbo_custom_images/CONTENT.txt
plonetheme/mimbo/skins/plonetheme_mimbo_custom_templates/CONTENT.txt
plonetheme/mimbo/skins/plonetheme_mimbo_styles/CONTENT.txt
plonetheme/mimbo/skins/plonetheme_mimbo_styles/base.css.dtml
plonetheme/mimbo/skins/plonetheme_mimbo_styles/base_properties.props
plonetheme/mimbo/skins/plonetheme_mimbo_styles/portlets.css.dtml
plonetheme/mimbo/skins/plonetheme_mimbo_styles/public.css.dtml