Metadata-Version: 1.0
Name: plonetheme.mimbo
Version: 0.4.1
Summary: An installable theme for Plone 3.0 based on the Mimbo theme by Darren Hoyt
Home-page: http://svn.plone.org/svn/collective/plonetheme.mimbo
Author: Timo Stollenwerk
Author-email: timo@zmag.de
License: GPL
Keywords: web zope plone theme
Platform: UNKNOWN
Classifier: Framework :: Plone
Classifier: Programming Language :: Python
Classifier: Topic :: Software Development :: Libraries :: Python Modules
